README.rst
setup.py
metricfactory/__init__.py
metricfactory/main.py
metricfactory.egg-info/PKG-INFO
metricfactory.egg-info/SOURCES.txt
metricfactory.egg-info/dependency_links.txt
metricfactory.egg-info/entry_points.txt
metricfactory.egg-info/namespace_packages.txt
metricfactory.egg-info/not-zip-safe
metricfactory.egg-info/requires.txt
metricfactory.egg-info/top_level.txt
metricfactory/decode/__init__.py
metricfactory/decode/elasticsearch.py
metricfactory/decode/ganglia.py
metricfactory/decode/modgearman.py
metricfactory/decode/rabbitmq.py
metricfactory/decode/rsyslog.py
metricfactory/encode/__init__.py
metricfactory/filter/__init__.py
metricfactory/filter/metricfilter.py
metricfactory/input/__init__.py
metricfactory/input/hammer.py