Metadata-Version: 1.1
Name: metricfactory
Version: 0.2.8
Summary: A set of Wishbone modules to consume, process and submit metrics.
Home-page: https://github.com/smetj/metricfactory
Author: Jelle Smet
Author-email: development@smetj.net
License: UNKNOWN
Download-URL: https://github.com/smetj/metricfactory/tarball/master
Platform: Linux
Classifier: Development Status :: 4 - Beta
Classifier: License :: OSI Approved :: GNU General Public License v3 or later (GPLv3+)
Classifier: Programming Language :: Python
Classifier: Programming Language :: Python :: 2
Classifier: Programming Language :: Python :: 2.6
Classifier: Programming Language :: Python :: 2.7
Classifier: Intended Audience :: Developers
Classifier: Intended Audience :: System Administrators
